{
  "intents": [
    {
      "intent": "AMAZON.CancelIntent"
    },
    {
      "intent": "AMAZON.HelpIntent"
    },
    {
      "intent": "AMAZON.StopIntent"
    },
    {
      "intent": "DepartureIntent"
    },
    {
      "intent": "StopIntent",
      "slots": [
        {
          "name": "stop",
          "type": "stopSlotType"
        }
      ]
    },
    {
      "intent": "RouteIntent",
      "slots": [
        {
          "name": "route",
          "type": "AMAZON.NUMBER"
        },
        {
          "name": "routePrefix",
          "type": "routePrefixSlotType"
        }
      ]
    }
  ]
}